CHANGES.rst
LICENSE
MANIFEST.in
README.rst
setup.py
SiftPartner.egg-info/PKG-INFO
SiftPartner.egg-info/SOURCES.txt
SiftPartner.egg-info/dependency_links.txt
SiftPartner.egg-info/requires.txt
SiftPartner.egg-info/top_level.txt
siftpartner/__init__.py
siftpartner/client.py
siftpartner/response.py
siftpartner/version.py