Metadata-Version: 1.1
Name: SiftPartner
Version: 0.0.3
Summary: Python bindings for Sift Science's Partnerships API
Home-page: https://siftscience.com
Author: Sift Science
Author-email: support@siftscience.com
License: UNKNOWN
Platform: UNKNOWN
Classifier: Programming Language :: Python
Classifier: Development Status :: 4 - Beta
Classifier: Intended Audience :: Developers
Classifier: License :: OSI Approved :: MIT License
Classifier: Topic :: Software Development :: Libraries :: Python Modules
